Metadata-Version: 2.1
Name: pinyintokenizer
Version: 0.0.2
Summary: Pinyin Tokenizer, chinese pinyin tokenizer
Home-page: https://github.com/shibing624/pinyin-tokenizer
Author: XuMing
Author-email: xuming624@qq.com
License: Apache 2.0
Keywords: pinyin-tokenizer,pinyin,pinyintokenizer,tokenizer
Platform: UNKNOWN
Classifier: Intended Audience :: Science/Research
Classifier: Operating System :: OS Independent
Classifier: License :: OSI Approved :: Apache Software License
Classifier: Programming Language :: Python
Classifier: Programming Language :: Python :: 2.7
Classifier: Programming Language :: Python :: 3
Classifier: Topic :: Text Processing :: Linguistic
Classifier: Topic :: Scientific/Engineering :: Artificial Intelligence
